chat_exporter/__init__.py
chat_exporter/chat_exporter.py
chat_exporter/construct/__init__.py
chat_exporter/construct/attachment_handler.py
chat_exporter/construct/message.py
chat_exporter/construct/transcript.py
chat_exporter/construct/assets/__init__.py
chat_exporter/construct/assets/attachment.py
chat_exporter/construct/assets/component.py
chat_exporter/construct/assets/embed.py
chat_exporter/construct/assets/reaction.py
chat_exporter/ext/__init__.py
chat_exporter/ext/cache.py
chat_exporter/ext/discord_import.py
chat_exporter/ext/discord_utils.py
chat_exporter/ext/discriminator.py
chat_exporter/ext/emoji_convert.py
chat_exporter/ext/html_generator.py
chat_exporter/html/__init__.py
chat_exporter/html/base.html
chat_exporter/html/attachment/audio.html
chat_exporter/html/attachment/image.html
chat_exporter/html/attachment/message.html
chat_exporter/html/attachment/video.html
chat_exporter/html/component/component_button.html
chat_exporter/html/component/component_menu.html
chat_exporter/html/component/component_menu_options.html
chat_exporter/html/component/component_menu_options_emoji.html
chat_exporter/html/embed/author.html
chat_exporter/html/embed/author_icon.html
chat_exporter/html/embed/body.html
chat_exporter/html/embed/description.html
chat_exporter/html/embed/field-inline.html
chat_exporter/html/embed/field.html
chat_exporter/html/embed/footer.html
chat_exporter/html/embed/footer_image.html
chat_exporter/html/embed/image.html
chat_exporter/html/embed/thumbnail.html
chat_exporter/html/embed/title.html
chat_exporter/html/message/bot-tag-verified.html
chat_exporter/html/message/bot-tag.html
chat_exporter/html/message/content.html
chat_exporter/html/message/end.html
chat_exporter/html/message/interaction.html
chat_exporter/html/message/message.html
chat_exporter/html/message/meta.html
chat_exporter/html/message/pin.html
chat_exporter/html/message/reference.html
chat_exporter/html/message/reference_unknown.html
chat_exporter/html/message/start.html
py_discord_html_transcripts-2.3.1.dist-info/METADATA
py_discord_html_transcripts-2.3.1.dist-info/WHEEL
py_discord_html_transcripts-2.3.1.dist-info/top_level.txt
py_discord_html_transcripts-2.3.1.dist-info/RECORD
